clang_format_all/__init__.py
clang_format_all/clang_format_all.py
clang_format_all-0.1.6.dist-info/LICENSE
clang_format_all-0.1.6.dist-info/METADATA
clang_format_all-0.1.6.dist-info/WHEEL
clang_format_all-0.1.6.dist-info/entry_points.txt
clang_format_all-0.1.6.dist-info/top_level.txt
clang_format_all-0.1.6.dist-info/RECORD
