Metadata-Version: 2.1
Name: clang-format-all
Version: 0.1.6
Summary: Format entire directories of source files with clang-format. This tool also allows to check for formatting without modifying files.
Author-email: Lorenzo Gomez <yunior.eury@gmail.com>
License: GNU GENERAL PUBLIC LICENSE
Project-URL: Homepage, https://github.com/thebigG/clang_format_all
Project-URL: Bug Tracker, https://github.com/thebigG/clang_format_all/issues
Classifier: Programming Language :: Python :: 3
Classifier: License :: OSI Approved :: GNU General Public License v3 (GPLv3)
Classifier: Operating System :: OS Independent
Requires-Python: >=3.7
License-File: LICENSE
Requires-Dist: pyyaml (==6.0)
